plico/__init__.py
plico/__version__.py
plico/client/__init__.py
plico/client/discovery.py
plico/client/hackerable_client.py
plico/client/serverinfo_client.py
plico/rpc/__init__.py
plico/rpc/abstract_remote_procedure_call.py
plico/rpc/dummy_remote_procedure_call.py
plico/rpc/dummy_sockets.py
plico/rpc/sockets.py
plico/rpc/zmq_ports.py
plico/rpc/zmq_remote_procedure_call.py
plico/types/__init__.py
plico/types/server_info.py
plico/types/zernike_coefficients.py
plico/utils/__init__.py
plico/utils/addtree.py
plico/utils/barrier.py
plico/utils/base_runner.py
plico/utils/calibration_installer.py
plico/utils/concurrent_loop.py
plico/utils/config_file_manager.py
plico/utils/configuration.py
plico/utils/constants.py
plico/utils/control_loop.py
plico/utils/convergeable.py
plico/utils/decorator.py
plico/utils/discovery_server.py
plico/utils/executor.py
plico/utils/fake_convergeable.py
plico/utils/fake_loop.py
plico/utils/fits_file_based_calibration_manager.py
plico/utils/hackerable.py
plico/utils/image_moments.py
plico/utils/kill_process_by_name.py
plico/utils/logger.py
plico/utils/loop.py
plico/utils/plico_scipy.py
plico/utils/process_monitor_runner.py
plico/utils/reconnect.py
plico/utils/sandbox.py
plico/utils/serial_or_usb_connection.py
plico/utils/serverinfoable.py
plico/utils/snapshotable.py
plico/utils/starter_script_creator_base.py
plico/utils/stepable.py
plico/utils/timekeeper.py
plico/utils/timeout.py
plico/utils/timestamp.py
plico/utils/zernike_generator.py
plico-0.33.0.dist-info/licenses/LICENSE
plico-0.33.0.dist-info/METADATA
plico-0.33.0.dist-info/WHEEL
plico-0.33.0.dist-info/top_level.txt
plico-0.33.0.dist-info/RECORD
