Metadata-Version: 2.4
Name: plico
Version: 0.33.0
Summary: Python Laboratory Instrumentation COntrol
Home-page: https://github.com/lbusoni/plico
Author: Lorenzo Busoni
Author-email: lorenzo.busoni@inaf.it
License: MIT
Keywords: laboratory,instrumentation controllaboratory,instrumentation control
Classifier: Development Status :: 4 - Beta
Classifier: Operating System :: POSIX :: Linux
Classifier: Programming Language :: Python :: 3
License-File: LICENSE
Requires-Dist: numpy
Requires-Dist: psutil
Requires-Dist: configparser
Requires-Dist: six
Requires-Dist: appdirs
Requires-Dist: pyzmq
Requires-Dist: futures; python_version == "2.7"
Requires-Dist: astropy
Requires-Dist: pyserial
Dynamic: author
Dynamic: author-email
Dynamic: classifier
Dynamic: description
Dynamic: description-content-type
Dynamic: home-page
Dynamic: keywords
Dynamic: license
Dynamic: license-file
Dynamic: requires-dist
Dynamic: summary
